unitforge-0.3.5.dist-info/METADATA
unitforge-0.3.5.dist-info/WHEEL
unitforge/__init__.py
unitforge/unitforge.cpython-312-x86_64-linux-gnu.so
unitforge-0.3.5.dist-info/RECORD
