Metadata-Version: 2.4
Name: unitforge
Version: 0.3.5
Classifier: Programming Language :: Python :: 3
Classifier: Programming Language :: Rust
Classifier: License :: OSI Approved :: MIT License
Classifier: Operating System :: OS Independent
Classifier: Topic :: Scientific/Engineering :: Physics
Requires-Dist: numpy>=2.2.0
Summary: A library for unit and quantity consistent computations in Rust
Keywords: units,quantities,simulation,physics
Author-email: "Dr.Q team" <info@askdrq.com>, Henrik Stromberg <henrik@askdrq.com>
Requires-Python: >=3.7
Project-URL: Repository, https://gitlab.com/henrikjstromberg/unitforge
